README.txt
setup.cfg
setup.py
docs/HISTORY.txt
docs/INSTALL.txt
docs/LICENSE.GPL
docs/LICENSE.txt
kreagroup/__init__.py
kreagroup.jsi18n.egg-info/PKG-INFO
kreagroup.jsi18n.egg-info/SOURCES.txt
kreagroup.jsi18n.egg-info/dependency_links.txt
kreagroup.jsi18n.egg-info/entry_points.txt
kreagroup.jsi18n.egg-info/namespace_packages.txt
kreagroup.jsi18n.egg-info/not-zip-safe
kreagroup.jsi18n.egg-info/paster_plugins.txt
kreagroup.jsi18n.egg-info/requires.txt
kreagroup.jsi18n.egg-info/top_level.txt
kreagroup/jsi18n/__init__.py
kreagroup/jsi18n/configure.zcml
kreagroup/jsi18n/interfaces.py
kreagroup/jsi18n/jsi18n.js
kreagroup/jsi18n/profiles/default/browserlayer.xml
kreagroup/jsi18n/profiles/default/metadata.xml
kreagroup/jsi18n/tests/__init__.py
kreagroup/jsi18n/tests/base.py
kreagroup/jsi18n/tests/test_dependencies.py
kreagroup/jsi18n/tests/test_setup.py