Metadata-Version: 1.1
Name: kreagroup.jsi18n
Version: 1.0.3
Summary: Plone i18n for JavaScript
Home-page: .
Author: Jochen Dekeyser
Author-email: ict@kreaplast.be
License: GPL
Keywords: plone JavaScript i18n krea.group jarn.jsi18n
Platform: UNKNOWN
Classifier: Framework :: Plone
Classifier: Programming Language :: Python
